molgemtools/__init__.py
molgemtools/constants.py
molgemtools/geom.py
molgemtools/graph.py
molgemtools/data/CH2Cl2.xyz
molgemtools/data/CH3Cl.xyz
molgemtools/data/CH4.xyz
molgemtools/data/H2O.xyz
molgemtools/data/HCl.xyz
molgemtools/data/NH3.xyz
molgemtools/data/water_molecules.xyz
molgemtools/data/alanine/ala_unknown_1.xyz
molgemtools/data/alanine/ala_unknown_2.xyz
molgemtools/data/alanine/ala_unknown_3.xyz
molgemtools/data/alanine/conformers/ala_1.xyz
molgemtools/data/alanine/conformers/ala_2.xyz
molgemtools/data/alanine/conformers/ala_3.xyz
molgemtools/data/alanine/conformers/ala_4.xyz
molgemtools-0.0.10.dist-info/LICENSE.txt
molgemtools-0.0.10.dist-info/METADATA
molgemtools-0.0.10.dist-info/WHEEL
molgemtools-0.0.10.dist-info/top_level.txt
molgemtools-0.0.10.dist-info/RECORD
