Metadata-Version: 2.1
Name: molgemtools
Version: 0.0.10
Summary: Tools for working with molecular geometry data.
Home-page: https://gitlab.com/d_attila/molgemtools.git
Author: Attila Dékány
Author-email: dekanyattilaadam@gmail.com
License: MIT
Project-URL: Documentation, https://d_attila.gitlab.io/molgemtools/
Project-URL: Source Code, https://gitlab.com/d_attila/molgemtools.git
Keywords: computational chemistry,molecular geometry,molecular shape matching,Z-matrix,Cartesian coordinates
Platform: any
Classifier: Programming Language :: Python :: 3
Classifier: Operating System :: OS Independent
Requires-Python: >=3.6
Requires-Dist: numpy
